Workbook
Name ing_names: Ingredients!$A$6:$A$40
Name ing_active: Ingredients!$O$6:$O$40
Name ing_unit: Ingredients!$B$6:$B$40
Name kiwi_cost: Recipes!$H$42
Name lemon_cost: Recipes!$I$42
Name caramel_cost: Recipes!$J$42
Name mint_cost: Recipes!$K$42
Name price_single: Pricing!$D$5
Name price_6pack: Pricing!$D$6
Name price_20pack: Pricing!$D$7
Name price_variety: Pricing!$D$8
Name price_whA: Pricing!$C$12
Name price_whB: Pricing!$C$13
Name price_whC: Pricing!$C$14
Name batch_total_capital: 'Batch Plan'!$D$10
Name batch_total_units: 'Batch Plan'!$B$10
Name avg_cost_per_pop: 'Batch Plan'!$D$10

Sheet README
A1: KIWI POP — Costing, Sourcing & Break-Even Workbook (v2)
A3: WHAT'S IN HERE
A4: 1. Ingredients 3-tier price list. Tier 1 = Amazon retail (today's production scale). Tier 2 = mid-tier wholesale
A5: (BulkSupplements wholesale portal, Jedwards, Bulk Apothecary, etc.). Tier 3 = factory-direct bulk
A6: (Nutri Avenue / Maxmedchem / Alibaba GMP, typically 25 kg MOQ). Pick the active tier in cell C2;
A7: prices flow through to every other sheet. Tier 3 prices are estimates where exact quotes aren't
A8: publicly listed — replace with real quotes as you get them.
A9: 2. Recipes Per-pop amounts for all 4 flavors. Edit the yellow amount columns to adjust formulation.
A10: Cost per pop is computed against the active tier on the Ingredients sheet.
A11: 3. Batch Plan Set a batch size per flavor (rounded to 20-cavity batches). See total ingredient capital
A12: required at each sourcing tier — that's the cheque you write before you make a single sale.
A13: 4. Pricing Retail SKU prices (single / 6-pack / 20-pack / variety) and wholesale tier prices.
... A48: DATE BUILT: May 2026

Sheet Ingredients
A1: INGREDIENTS — 3-Tier Sourcing Master Price List
A2: Active sourcing tier (drives prices everywhere else): | C2: Tier 1 — Amazon (now)
A4: Ingredient | B4: Unit | C4: Tier 1 — Amazon retail (current) | F4: Tier 2 — Mid wholesale (next step) | I4: Tier 3 — Large bulk (scaled production) | L4: Cost per unit (auto) | O4: Active $/unit | P4: Notes
C5: Pkg size | D5: Pkg price ($) | E5: Link | F5: Pkg size | G5: Pkg price ($) | H5: Link | I5: Pkg size | J5: Pkg price ($) | K5: Link | L5: T1 $/unit | M5: T2 $/unit | N5: T3 $/unit
A6: Isomalt | B6: g | C6: 2270 | D6: 35 | E6: View source | F6: 10000 | G6: 120 | H6: View source | I6: 22680 | J6: 200 | K6: View source | L6: =IFERROR(D6/C6,0) | M6: =IFERROR(G6/F6,0) | N6: =IFERROR(J6/I6,0) | O6: =IF($C$2="Tier 1 — Amazon (now)",L6,IF($C$2="Tier 2 — Mid wholesale",M6,N6)) | P6: CK Products 5lb on Amazon; Bakers Authority 45lb; Webstaurant bulk.
A7: Water (filtered) | B7: ml | C7: 1000 | D7: 0 | E7: — | F7: 1000 | G7: 0 | H7: — | I7: 1000 | J7: 0 | K7: — | L7: =IFERROR(D7/C7,0) | M7: =IFERROR(G7/F7,0) | N7: =IFERROR(J7/I7,0) | O7: =IF($C$2="Tier 1 — Amazon (now)",L7,IF($C$2="Tier 2 — Mid wholesale",M7,N7)) | P7: Tap/filtered — effectively free.
A8: Monk fruit extract | B8: g | C8: 454 | D8: 20 | E8: View source | F8: 5000 | G8: 150 | H8: View source | I8: 25000 | J8: 500 | K8: View source | L8: =IFERROR(D8/C8,0) | M8: =IFERROR(G8/F8,0) | N8: =IFERROR(J8/I8,0) | O8: =IF($C$2="Tier 1 — Amazon (now)",L8,IF($C$2="Tier 2 — Mid wholesale",M8,N8)) | P8: BulkSupplements 1lb on Amazon; wholesale portal for 5kg; Nutri Avenue 25kg factory.
A9: Xylitol | B9: g | C9: 1360 | D9: 20 | E9: View source | F9: 9070 | G9: 90 | H9: View source | I9: 22680 | J9: 180 | K9: View source | L9: =IFERROR(D9/C9,0) | M9: =IFERROR(G9/F9,0) | N9: =IFERROR(J9/I9,0) | O9: =IF($C$2="Tier 1 — Amazon (now)",L9,IF($C$2="Tier 2 — Mid wholesale",M9,N9)) | P9: Anthony's 3lb Amazon; Webstaurant 20lb; Bulk Apothecary 50lb.
A10: Coconut oil (refined) | B10: g | C10: 858 | D10: 14 | E10: View source | F10: 4000 | G10: 50 | H10: View source | I10: 17000 | J10: 130 | K10: View source | L10: =IFERROR(D10/C10,0) | M10: =IFERROR(G10/F10,0) | N10: =IFERROR(J10/I10,0) | O10: =IF($C$2="Tier 1 — Amazon (now)",L10,IF($C$2="Tier 2 — Mid wholesale",M10,N10)) | P10: Spectrum 30oz Amazon; Webstaurant gallon; Jedwards 5gal.
A11: Jambu oleoresin (8-10% spilanthol) | B11: g | C11: 30 | D11: 80 | E11: View source | F11: 100 | G11: 200 | H11: View source | I11: 1000 | J11: 1200 | K11: View source | L11: =IFERROR(D11/C11,0) | M11: =IFERROR(G11/F11,0) | N11: =IFERROR(J11/I11,0) | O11: =IF($C$2="Tier 1 — Amazon (now)",L11,IF($C$2="Tier 2 — Mid wholesale",M11,N11)) | P11: Specialty. Nativilis on Amazon is cosmetic-grade — for food use, source S.A. Herbal Bioactives or Ingredients Online direct.
A12: Theobromine powder | B12: g | C12: 1000 | D12: 30 | E12: View source | F12: 5000 | G12: 110 | H12: View source | I12: 25000 | J12: 400 | K12: View source | L12: =IFERROR(D12/C12,0) | M12: =IFERROR(G12/F12,0) | N12: =IFERROR(J12/I12,0) | O12: =IF($C$2="Tier 1 — Amazon (now)",L12,IF($C$2="Tier 2 — Mid wholesale",M12,N12)) | P12: BulkSupplements 1kg on Amazon; wholesale portal 5kg; Nutri Avenue 25kg drum.
A13: Magnesium glycinate powder | B13: g | C13: 1000 | D13: 25 | E13: View source | F13: 5000 | G13: 90 | H13: View source | I13: 25000 | J13: 350 | K13: View source | L13: =IFERROR(D13/C13,0) | M13: =IFERROR(G13/F13,0) | N13: =IFERROR(J13/I13,0) | O13: =IF($C$2="Tier 1 — Amazon (now)",L13,IF($C$2="Tier 2 — Mid wholesale",M13,N13)) | P13: BulkSupplements 1kg; wholesale 5kg; Maxmedchem 25kg MOQ.
A14: Taurine powder | B14: g | C14: 1000 | D14: 20 | E14: View source | F14: 5000 | G14: 75 | H14: View source | I14: 25000 | J14: 250 | K14: View source | L14: =IFERROR(D14/C14,0) | M14: =IFERROR(G14/F14,0) | N14: =IFERROR(J14/I14,0) | O14: =IF($C$2="Tier 1 — Amazon (now)",L14,IF($C$2="Tier 2 — Mid wholesale",M14,N14)) | P14: BulkSupplements 1kg; wholesale; Nutri Avenue factory.
A15: B12 (methylcobalamin) powder | B15: g | C15: 10 | D15: 15 | E15: View source | F15: 100 | G15: 100 | H15: View source | I15: 1000 | J15: 700 | K15: View source | L15: =IFERROR(D15/C15,0) | M15: =IFERROR(G15/F15,0) | N15: =IFERROR(J15/I15,0) | O15: =IF($C$2="Tier 1 — Amazon (now)",L15,IF($C$2="Tier 2 — Mid wholesale",M15,N15)) | P15: Tiny dose — 10g lasts thousands of pops at 1mg each.
A16: Sacred Eats Keto Recharge electrolyte blend | B16: g | C16: 325 | D16: 36.97 | E16: View source | F16: 3250 | G16: 300 | H16: View source | I16: 32500 | J16: 2400 | K16: View source | L16: =IFERROR(D16/C16,0) | M16: =IFERROR(G16/F16,0) | N16: =IFERROR(J16/I16,0) | O16: =IF($C$2="Tier 1 — Amazon (now)",L16,IF($C$2="Tier 2 — Mid wholesale",M16,N16)) | P16: Brand-specific blend. Direct wholesale via Sacred Eats — contact for bulk.
A17: Ginseng extract powder | B17: g | C17: 500 | D17: 25 | E17: View source | F17: 5000 | G17: 180 | H17: View source | I17: 25000 | J17: 600 | K17: View source | L17: =IFERROR(D17/C17,0) | M17: =IFERROR(G17/F17,0) | N17: =IFERROR(J17/I17,0) | O17: =IF($C$2="Tier 1 — Amazon (now)",L17,IF($C$2="Tier 2 — Mid wholesale",M17,N17)) | P17: For Kiwi Pop v2.0.
... A40: Neutral cooking spray (release agent) | B40: ml | C40: 170 | D40: 5 | E40: View source | F40: 600 | G40: 12 | H40: View source | I40: 3785 | J40: 30 | K40: View source | L40: =IFERROR(D40/C40,0) | M40: =IFERROR(G40/F40,0) | N40: =IFERROR(J40/I40,0) | O40: =IF($C$2="Tier 1 — Amazon (now)",L40,IF($C$2="Tier 2 — Mid wholesale",M40,N40)) | P40: Tiny per-pop usage. Mostly negligible cost.

Sheet Recipes
A1: RECIPES — Per-Pop Amounts & Cost (live against active tier)
A2: Active tier: | B2: =Ingredients!C2
A4: Ingredient | B4: Unit | C4: Active $/unit | D4: Amount / pop | H4: Cost / pop
D5: Kiwi Pop | E5: Lemon Ginger | F5: Caramel Apple | G5: Mint | H5: Kiwi Pop | I5: Lemon Ginger | J5: Caramel Apple | K5: Mint
A6: Isomalt | B6: g | C6: =Ingredients!O6 | D6: 15 | E6: 15 | F6: 15 | G6: 15 | H6: =D6*$C$6 | I6: =E6*$C$6 | J6: =F6*$C$6 | K6: =G6*$C$6
A7: Water (filtered) | B7: ml | C7: =Ingredients!O7 | D7: 4 | E7: 4 | F7: 4 | G7: 4 | H7: =D7*$C$7 | I7: =E7*$C$7 | J7: =F7*$C$7 | K7: =G7*$C$7
A8: Monk fruit extract | B8: g | C8: =Ingredients!O8 | D8: 0.06 | E8: 0.06 | F8: 0.06 | G8: 0.06 | H8: =D8*$C$8 | I8: =E8*$C$8 | J8: =F8*$C$8 | K8: =G8*$C$8
A9: Xylitol | B9: g | C9: =Ingredients!O9 | D9: 1.2 | E9: 1.2 | F9: 1.2 | G9: 1.2 | H9: =D9*$C$9 | I9: =E9*$C$9 | J9: =F9*$C$9 | K9: =G9*$C$9
A10: Coconut oil (refined) | B10: g | C10: =Ingredients!O10 | D10: 0.2 | E10: 0.2 | F10: 0.2 | G10: 0.2 | H10: =D10*$C$10 | I10: =E10*$C$10 | J10: =F10*$C$10 | K10: =G10*$C$10
A11: Jambu oleoresin (8-10% spilanthol) | B11: g | C11: =Ingredients!O11 | D11: 0.05 | E11: 0.05 | F11: 0.05 | G11: 0.05 | H11: =D11*$C$11 | I11: =E11*$C$11 | J11: =F11*$C$11 | K11: =G11*$C$11
A12: Theobromine powder | B12: g | C12: =Ingredients!O12 | D12: 0.175 | E12: 0.175 | F12: 0.175 | G12: 0.175 | H12: =D12*$C$12 | I12: =E12*$C$12 | J12: =F12*$C$12 | K12: =G12*$C$12
A13: Magnesium glycinate powder | B13: g | C13: =Ingredients!O13 | D13: 0.3 | E13: 0.3 | F13: 0.3 | G13: 0.3 | H13: =D13*$C$13 | I13: =E13*$C$13 | J13: =F13*$C$13 | K13: =G13*$C$13
A14: Taurine powder | B14: g | C14: =Ingredients!O14 | D14: 0.25 | E14: 0.25 | F14: 0.25 | G14: 0.25 | H14: =D14*$C$14 | I14: =E14*$C$14 | J14: =F14*$C$14 | K14: =G14*$C$14
A15: B12 (methylcobalamin) powder | B15: g | C15: =Ingredients!O15 | D15: 0.001 | E15: 0.001 | F15: 0.001 | G15: 0.001 | H15: =D15*$C$15 | I15: =E15*$C$15 | J15: =F15*$C$15 | K15: =G15*$C$15
A16: Sacred Eats Keto Recharge electrolyte blend | B16: g | C16: =Ingredients!O16 | D16: 0.25 | E16: 0.25 | F16: 0.25 | G16: 0.25 | H16: =D16*$C$16 | I16: =E16*$C$16 | J16: =F16*$C$16 | K16: =G16*$C$16
A17: Ginseng extract powder | B17: g | C17: =Ingredients!O17 | D17: 0.15 | E17: 0 | F17: 0 | G17: 0 | H17: =D17*$C$17 | I17: =E17*$C$17 | J17: =F17*$C$17 | K17: =G17*$C$17
A18: Spirulina powder (organic) | B18: g | C18: =Ingredients!O18 | D18: 0.5 | E18: 0 | F18: 0 | G18: 0 | H18: =D18*$C$18 | I18: =E18*$C$18 | J18: =F18*$C$18 | K18: =G18*$C$18
A19: Ashwagandha root extract powder | B19: g | C19: =Ingredients!O19 | D19: 0 | E19: 0.15 | F19: 0 | G19: 0 | H19: =D19*$C$19 | I19: =E19*$C$19 | J19: =F19*$C$19 | K19: =G19*$C$19
A20: Maca powder (organic) | B20: g | C20: =Ingredients!O20 | D20: 0 | E20: 0 | F20: 0.15 | G20: 0 | H20: =D20*$C$20 | I20: =E20*$C$20 | J20: =F20*$C$20 | K20: =G20*$C$20
A21: L-theanine powder | B21: g | C21: =Ingredients!O21 | D21: 0 | E21: 0 | F21: 0 | G21: 0.2 | H21: =D21*$C$21 | I21: =E21*$C$21 | J21: =F21*$C$21 | K21: =G21*$C$21
A22: Chamomile extract powder | B22: g | C22: =Ingredients!O22 | D22: 0 | E22: 0 | F22: 0 | G22: 0.025 | H22: =D22*$C$22 | I22: =E22*$C$22 | J22: =F22*$C$22 | K22: =G22*$C$22
A23: Kiwi powder (freeze-dried) | B23: g | C23: =Ingredients!O23 | D23: 0.6 | E23: 0 | F23: 0 | G23: 0 | H23: =D23*$C$23 | I23: =E23*$C$23 | J23: =F23*$C$23 | K23: =G23*$C$23
A24: Lemon powder (freeze-dried) | B24: g | C24: =Ingredients!O24 | D24: 0 | E24: 0.6 | F24: 0 | G24: 0 | H24: =D24*$C$24 | I24: =E24*$C$24 | J24: =F24*$C$24 | K24: =G24*$C$24
A25: Ginger powder (organic ground) | B25: g | C25: =Ingredients!O25 | D25: 0 | E25: 0.5 | F25: 0 | G25: 0 | H25: =D25*$C$25 | I25: =E25*$C$25 | J25: =F25*$C$25 | K25: =G25*$C$25
A26: Turmeric extract (95% curcumin) | B26: g | C26: =Ingredients!O26 | D26: 0 | E26: 0.025 | F26: 0 | G26: 0 | H26: =D26*$C$26 | I26: =E26*$C$26 | J26: =F26*$C$26 | K26: =G26*$C$26
A27: Apple powder (freeze-dried) | B27: g | C27: =Ingredients!O27 | D27: 0 | E27: 0 | F27: 0.9 | G27: 0 | H27: =D27*$C$27 | I27: =E27*$C$27 | J27: =F27*$C$27 | K27: =G27*$C$27
A28: Lucuma powder (organic) | B28: g | C28: =Ingredients!O28 | D28: 0 | E28: 0 | F28: 0.3 | G28: 0 | H28: =D28*$C$28 | I28: =E28*$C$28 | J28: =F28*$C$28 | K28: =G28*$C$28
A29: Caramel extract (natural) | B29: ml | C29: =Ingredients!O29 | D29: 0 | E29: 0 | F29: 0.1 | G29: 0 | H29: =D29*$C$29 | I29: =E29*$C$29 | J29: =F29*$C$29 | K29: =G29*$C$29
A30: Cinnamon powder (Ceylon) | B30: g | C30: =Ingredients!O30 | D30: 0 | E30: 0 | F30: 0.1 | G30: 0 | H30: =D30*$C$30 | I30: =E30*$C$30 | J30: =F30*$C$30 | K30: =G30*$C$30
A31: Matcha powder (culinary grade) | B31: g | C31: =Ingredients!O31 | D31: 0 | E31: 0 | F31: 0 | G31: 0.05 | H31: =D31*$C$31 | I31: =E31*$C$31 | J31: =F31*$C$31 | K31: =G31*$C$31
A32: Peppermint essential oil (food grade) | B32: ml | C32: =Ingredients!O32 | D32: 0 | E32: 0 | F32: 0 | G32: 0.0125 | H32: =D32*$C$32 | I32: =E32*$C$32 | J32: =F32*$C$32 | K32: =G32*$C$32
A33: Spearmint essential oil (food grade) | B33: ml | C33: =Ingredients!O33 | D33: 0 | E33: 0 | F33: 0 | G33: 0.0075 | H33: =D33*$C$33 | I33: =E33*$C$33 | J33: =F33*$C$33 | K33: =G33*$C$33
A34: Citric acid (food grade) | B34: g | C34: =Ingredients!O34 | D34: 0.25 | E34: 0.25 | F34: 0.1 | G34: 0.05 | H34: =D34*$C$34 | I34: =E34*$C$34 | J34: =F34*$C$34 | K34: =G34*$C$34
A35: Edible glitter (gold/bronze/silver) | B35: g | C35: =Ingredients!O35 | D35: 0.1 | E35: 0.1 | F35: 0.1 | G35: 0.1 | H35: =D35*$C$35 | I35: =E35*$C$35 | J35: =F35*$C$35 | K35: =G35*$C$35
A36: Lollipop sticks (paper or bamboo) | B36: ea | C36: =Ingredients!O36 | D36: 1 | E36: 1 | F36: 1 | G36: 1 | H36: =D36*$C$36 | I36: =E36*$C$36 | J36: =F36*$C$36 | K36: =G36*$C$36
A37: Lollipop wrapper (clear cello + heat seal) | B37: ea | C37: =Ingredients!O37 | D37: 1 | E37: 1 | F37: 1 | G37: 1 | H37: =D37*$C$37 | I37: =E37*$C$37 | J37: =F37*$C$37 | K37: =G37*$C$37
A38: Sticker / label per pop | B38: ea | C38: =Ingredients!O38 | D38: 1 | E38: 1 | F38: 1 | G38: 1 | H38: =D38*$C$38 | I38: =E38*$C$38 | J38: =F38*$C$38 | K38: =G38*$C$38
A39: Silicone mold (amortized cavity-uses) | B39: ea | C39: =Ingredients!O39 | D39: 1 | E39: 1 | F39: 1 | G39: 1 | H39: =D39*$C$39 | I39: =E39*$C$39 | J39: =F39*$C$39 | K39: =G39*$C$39
A40: Neutral cooking spray (release agent) | B40: ml | C40: =Ingredients!O40 | D40: 0.05 | E40: 0.05 | F40: 0.05 | G40: 0.05 | H40: =D40*$C$40 | I40: =E40*$C$40 | J40: =F40*$C$40 | K40: =G40*$C$40
A42: COST PER POP | H42: =SUM(H6:H40) | I42: =SUM(I6:I40) | J42: =SUM(J6:J40) | K42: =SUM(K6:K40)

Sheet Pricing
A1: PRICING — Retail SKUs & Wholesale Tiers
A3: RETAIL SKUs
A4: SKU | B4: Pops per unit | C4: Price per unit | D4: Effective $/pop | E4: Notes
A5: Single pop | B5: 1 | C5: 5 | D5: =C5/B5
A6: 6-pack | B6: 6 | C6: 25 | D6: =C6/B6
A7: 20-pack (Party Pack) | B7: 20 | C7: 60 | D7: =C7/B7
A8: Variety 12-pack (preorder) | B8: 12 | C8: 24 | D8: =C8/B8
A10: WHOLESALE TIERS
A11: Tier | B11: Min units | C11: $/pop (wholesale) | E11: Notes
A12: Tier A — Small (1-49) | B12: 1 | C12: 2.5
A13: Tier B — Medium (50-199) | B13: 50 | C13: 2
A14: Tier C — Large (200+) | B14: 200 | C14: 1.65

Sheet Batch Plan
A1: BATCH PLAN — Ingredient Capital Required (active tier)
A2: Active tier: | B2: =Ingredients!C2
A4: Flavor | B4: Pops to make | C4: Cost / pop | D4: Ingredient capital | E4: Notes
A5: Kiwi Pop | B5: 100 | C5: =kiwi_cost | D5: =B5*C5
A6: Lemon Ginger | B6: 100 | C6: =lemon_cost | D6: =B6*C6
A7: Caramel Apple | B7: 100 | C7: =caramel_cost | D7: =B7*C7
A8: Mint | B8: 100 | C8: =mint_cost | D8: =B8*C8
A10: TOTAL | B10: =SUM(B5:B8) | D10: =SUM(D5:D8)
A12: Tip: switch the active tier on the Ingredients tab to see how capital required drops when you scale up. The cost/pop column will recompute automatically.

Sheet Break-Even
A1: BREAK-EVEN — Units to sell to recover this batch's ingredient capital
A2: Capital to recover (from Batch Plan): | B2: =batch_total_capital
A3: Avg ingredient cost per pop in this batch: | B3: =IFERROR(batch_total_capital/batch_total_units,0)
A5: If you sold 100% through ONE channel, you'd hit break-even at:
A6: Channel | B6: $/pop received | C6: Profit/pop | D6: Pops to break even | E6: % of batch sold | F6: Notes
A7: Retail · single ($5) | B7: =price_single | C7: =B7-$B$3 | D7: =IF(C7<=0,"NEVER (sells below cost)",ROUNDUP($B$2/C7,0)) | E7: =IFERROR(IF(C7<=0,"-",D7/batch_total_units),"-") | F7: Highest margin, slowest volume.
A8: Retail · 6-pack ($4.17/pop) | B8: =price_6pack | C8: =B8-$B$3 | D8: =IF(C8<=0,"NEVER (sells below cost)",ROUNDUP($B$2/C8,0)) | E8: =IFERROR(IF(C8<=0,"-",D8/batch_total_units),"-") | F8: Strong DTC margin.
A9: Retail · 20-pack ($3.00/pop) | B9: =price_20pack | C9: =B9-$B$3 | D9: =IF(C9<=0,"NEVER (sells below cost)",ROUNDUP($B$2/C9,0)) | E9: =IFERROR(IF(C9<=0,"-",D9/batch_total_units),"-") | F9: Volume DTC.
A10: Retail · variety preorder ($2) | B10: =price_variety | C10: =B10-$B$3 | D10: =IF(C10<=0,"NEVER (sells below cost)",ROUNDUP($B$2/C10,0)) | E10: =IFERROR(IF(C10<=0,"-",D10/batch_total_units),"-") | F10: Preorder discount tier.
A11: Wholesale A — small (1-49) | B11: =price_whA | C11: =B11-$B$3 | D11: =IF(C11<=0,"NEVER (sells below cost)",ROUNDUP($B$2/C11,0)) | E11: =IFERROR(IF(C11<=0,"-",D11/batch_total_units),"-") | F11: Tasting-room / single-shop orders.
A12: Wholesale B — medium (50-199) | B12: =price_whB | C12: =B12-$B$3 | D12: =IF(C12<=0,"NEVER (sells below cost)",ROUNDUP($B$2/C12,0)) | E12: =IFERROR(IF(C12<=0,"-",D12/batch_total_units),"-") | F12: Standard wholesale tier.
A13: Wholesale C — large (200+) | B13: =price_whC | C13: =B13-$B$3 | D13: =IF(C13<=0,"NEVER (sells below cost)",ROUNDUP($B$2/C13,0)) | E13: =IFERROR(IF(C13<=0,"-",D13/batch_total_units),"-") | F13: Distributor / chain account.
A16: MIXED-CHANNEL CALCULATOR — type the SHARE of each channel below (must sum to 100%). The output is how many TOTAL pops you'd need to sell in that mix to break even.
A18: Channel | B18: Share % | C18: $/pop
A19: Retail · single ($5) | B19: 0.1 | C19: =price_single
A20: Retail · 6-pack ($4.17/pop) | B20: 0.15 | C20: =price_6pack
A21: Retail · 20-pack ($3.00/pop) | B21: 0.15 | C21: =price_20pack
A22: Retail · variety preorder ($2) | B22: 0 | C22: =price_variety
A23: Wholesale A — small (1-49) | B23: 0.1 | C23: =price_whA
A24: Wholesale B — medium (50-199) | B24: 0.4 | C24: =price_whB
A25: Wholesale C — large (200+) | B25: 0.1 | C25: =price_whC
A26: Total share | B26: =SUM(B19:B25)
A28: Weighted avg $/pop | B28: =SUMPRODUCT(B19:B25,C19:C25)
A29: Profit per pop (avg) | B29: =B28-$B$3
A30: Pops to break even (this mix) | B30: =IF(B29<=0,"NEVER",ROUNDUP($B$2/B29,0))

Sheet Scenario
A1: SCENARIO — Plug in your real sales mix, see the bottom line
A2: Active tier: | B2: =Ingredients!C2
A3: Labor + overhead multiplier (×COGS): | B3: 0.4
A4: Fixed costs this period ($): | B4: 0
A6: Channel \ Flavor → | B6: Kiwi Pop | C6: Lemon Ginger | D6: Caramel Apple | E6: Mint | F6: Units total | G6: $/pop | H6: Revenue | I6: COGS (ingred) | J6: Gross profit
A7: Retail · single | B7: 0 | C7: 0 | D7: 0 | E7: 0 | F7: =SUM(B7:E7) | G7: =price_single | H7: =F7*G7 | I7: =B7*kiwi_cost+C7*lemon_cost+D7*caramel_cost+E7*mint_cost | J7: =H7-I7
A8: Retail · 6-pack | B8: 0 | C8: 0 | D8: 0 | E8: 0 | F8: =SUM(B8:E8) | G8: =price_6pack | H8: =F8*G8 | I8: =B8*kiwi_cost+C8*lemon_cost+D8*caramel_cost+E8*mint_cost | J8: =H8-I8
A9: Retail · 20-pack | B9: 0 | C9: 0 | D9: 0 | E9: 0 | F9: =SUM(B9:E9) | G9: =price_20pack | H9: =F9*G9 | I9: =B9*kiwi_cost+C9*lemon_cost+D9*caramel_cost+E9*mint_cost | J9: =H9-I9
A10: Retail · variety pre | B10: 0 | C10: 0 | D10: 0 | E10: 0 | F10: =SUM(B10:E10) | G10: =price_variety | H10: =F10*G10 | I10: =B10*kiwi_cost+C10*lemon_cost+D10*caramel_cost+E10*mint_cost | J10: =H10-I10
A11: Wholesale A | B11: 0 | C11: 0 | D11: 0 | E11: 0 | F11: =SUM(B11:E11) | G11: =price_whA | H11: =F11*G11 | I11: =B11*kiwi_cost+C11*lemon_cost+D11*caramel_cost+E11*mint_cost | J11: =H11-I11
A12: Wholesale B | B12: 0 | C12: 0 | D12: 0 | E12: 0 | F12: =SUM(B12:E12) | G12: =price_whB | H12: =F12*G12 | I12: =B12*kiwi_cost+C12*lemon_cost+D12*caramel_cost+E12*mint_cost | J12: =H12-I12
A13: Wholesale C | B13: 0 | C13: 0 | D13: 0 | E13: 0 | F13: =SUM(B13:E13) | G13: =price_whC | H13: =F13*G13 | I13: =B13*kiwi_cost+C13*lemon_cost+D13*caramel_cost+E13*mint_cost | J13: =H13-I13
A15: TOTAL | B15: =SUM(B7:B13) | C15: =SUM(C7:C13) | D15: =SUM(D7:D13) | E15: =SUM(E7:E13) | F15: =SUM(F7:F13) | H15: =SUM(H7:H13) | I15: =SUM(I7:I13) | J15: =SUM(J7:J13)
A17: P&L SUMMARY
A18: Revenue: | B18: =H15
A19: COGS (ingredients): | B19: =I15
A20: Labor + overhead: | B20: =I15*$B$3
A21: Fixed costs: | B21: =$B$4
A22: Net profit: | B22: =H15-I15-I15*$B$3-$B$4
A23: Net margin %: | B23: =IFERROR((H15-I15-I15*$B$3-$B$4)/H15,0)
A24: Total units sold: | B24: =F15
A26: HOW TO USE: Type units sold per flavor per channel in the yellow grid. Adjust labor multiplier (default 40% of COGS — covers your hands-on time + utilities) and fixed costs (rent, marketing, platform fees for the period). Switch the active sourcing tier on the Ingredients sheet to see how the P&L changes when you scale up purchasing.
